setup.py
py_geoinova_mongolog/__init__.py
py_geoinova_mongolog/mongolog.py
py_geoinova_mongolog.egg-info/PKG-INFO
py_geoinova_mongolog.egg-info/SOURCES.txt
py_geoinova_mongolog.egg-info/dependency_links.txt
py_geoinova_mongolog.egg-info/top_level.txt