Metadata-Version: 1.0
Name: py-geoinova-mongolog
Version: 1.2
Summary: Pacote responsável por salvar as informações de log no mongo
Home-page: UNKNOWN
Author: Manoel Neco Jr
Author-email: manoel.junior@geoinova.com.br
License: UNKNOWN
Platform: UNKNOWN
